sxapi/__init__.py
sxapi/ext.py
sxapi/helper.py
sxapi/low.py
sxapi/models.py
tests/__init__.py
tests/test_flask.py
tests/test_highapi.py
tests/test_lowapi.py
tests/util.py
sxapi-0.15.dist-info/LICENSE
sxapi-0.15.dist-info/METADATA
sxapi-0.15.dist-info/WHEEL
sxapi-0.15.dist-info/top_level.txt
sxapi-0.15.dist-info/RECORD
