Metadata-Version: 2.1
Name: sxapi
Version: 0.15
Summary: smaXtec API client
Home-page: UNKNOWN
Author: Matthias Wutte
Author-email: matthias.wutte@gmail.com
License: UNKNOWN
Download-URL: https://github.com/smaxtec/sxapi_legacy
Platform: UNKNOWN
License-File: LICENSE
Requires-Dist: requests
Requires-Dist: pendulum (>=2.0.2)
